phonesensors/__init__.py
phonesensors/client.py
phonesensors/containers.py
phonesensors/parsers.py
phonesensors/sources.py
phonesensors/tests/__init__.py
phonesensors/tests/unit/__init__.py
phonesensors/tests/unit/test_client.py
phonesensors/tests/unit/test_parsers.py
phonesensors-1.0.0.dist-info/METADATA
phonesensors-1.0.0.dist-info/WHEEL
phonesensors-1.0.0.dist-info/licenses/LICENSE
phonesensors-1.0.0.dist-info/RECORD
