Metadata-Version: 2.1
Name: phonesensors
Version: 1.0.0
Summary: A package for receiving data from sensor-streaming phone apps.
Project-URL: Homepage, https://github.com/nup002/PhoneSensors
Project-URL: Bug Tracker, https://github.com/nup002/PhoneSensors/issues
Author-email: Magne Eik Lauritzen <mag.lauritzen@gmail.com>
License: MIT License
License-File: LICENSE
Classifier: License :: OSI Approved :: MIT License
Classifier: Operating System :: OS Independent
Classifier: Programming Language :: Python :: 3
Requires-Python: >=3.7
Requires-Dist: numpy
